ques3.v
module ques3(a,b,c,s,f);
    input a,b,c;
    output f,s;
    wire [0:1]W1;
    wire [0:1]W2;
    wire [0:1]W3;
    wire g1;
    wire g2;
    wire g3;
    assign W1 = {a, ~a};
    assign W2 = {1'b0, a};
    assign W3 = {a, 1'b1};
    mux2to1 m1(W1,b, g1);
    mux2to1 m2({g1, ~g1},c, s);
    mux2to1 m3(W2,b, g2);
    mux2to1 m4(W3,b,g3);
    mux2to1 m5({g2,g3},c,f);
endmodule

module mux2to1(W,S,f);
    input [0:1]W;
    input S;
    output reg f;
    always@(W or S)
        if(S==0)
            f = W[0];
        else 
            f = W[1];
endmodule

ques3_tb.v
`timescale 1ns/1ns
`include "ques3.v"

module ques3_tb();
    reg a, b, c;
    wire f;
    ques3 test(a, b, c, s, f);
    initial begin
        $dumpfile("ques3.vcd");
        $dumpvars(1,ques3_tb);
        c=1'b0; a=1'b0; b=1'b0; #10;
        c=1'b0; a=1'b0; b=1'b1; #10;
        c=1'b0; a=1'b1; b=1'b0; #10;
        c=1'b0; a=1'b1; b=1'b1; #10;
        c=1'b1; a=1'b0; b=1'b0; #10;
        c=1'b1; a=1'b0; b=1'b1; #10;
        c=1'b1; a=1'b1; b=1'b0; #10;
        c=1'b1; a=1'b1; b=1'b1; #10;
        $display("Test completed");
    end
endmodule

ques3.vcd
$date
	Tue Oct  4 10:41:13 2022
$end
$version
	Icarus Verilog
$end
$timescale
	1ns
$end
$scope module ques3_tb $end
$var wire 1 ! s $end
$var wire 1 " f $end
$var reg 1 # a $end
$var reg 1 $ b $end
$var reg 1 % c $end
$upscope $end
$enddefinitions $end
#0
$dumpvars
0%
0$
0#
0"
0!
$end
#10
1!
1$
#20
0$
1#
#30
0!
1"
1$
#40
0"
1!
0$
0#
1%
#50
0!
1"
1$
#60
0$
1#
#70
1!
1$
