ques2b.v
module ques2b(a,b,c,f);
    input a,b,c;
    output f;
    mux2to1 m2({b&c, b|c},a, f);
endmodule

module mux2to1(W,S,f);
    input [0:1]W;
    input S;
    output reg f;
    always@(W or S)
        if(S==0)
            f = W[0];
        else 
            f = W[1];
endmodule

ques2b_tb.v
`timescale 1ns/1ns
`include "ques2b.v"

module ques2b_tb();
    reg a, b, c;
    wire f;
    ques2b test(a, b, c, f);
    initial begin
        $dumpfile("ques2b.vcd");
        $dumpvars(1,ques2b_tb);
        a=1'b0; b=1'b0; c=1'b0; #10;
        a=1'b0; b=1'b0; c=1'b1; #10;
        a=1'b0; b=1'b1; c=1'b0; #10;
        a=1'b0; b=1'b1; c=1'b1; #10;
        a=1'b1; b=1'b0; c=1'b0; #10;
        a=1'b1; b=1'b0; c=1'b1; #10;
        a=1'b1; b=1'b1; c=1'b0; #10;
        a=1'b1; b=1'b1; c=1'b1; #10;
        $display("Test completed");
    end
endmodule

ques2b.vcd
$date
	Tue Oct  4 11:01:09 2022
$end
$version
	Icarus Verilog
$end
$timescale
	1ns
$end
$scope module ques2b_tb $end
$var wire 1 ! f $end
$var reg 1 " a $end
$var reg 1 # b $end
$var reg 1 $ c $end
$upscope $end
$enddefinitions $end
#0
$dumpvars
0$
0#
0"
0!
$end
#10
1$
#20
0$
1#
#30
1!
1$
#40
0!
0$
0#
1"
#50
1!
1$
#60
0$
1#
#70
1$
