ques1b.v
module ques1b(a,b,c,d,f);
    input a,b,c,d;
    output f;
    wire [0:3]W;
    wire [1:0]S;
    wire g;
    assign W = {d, 1'b1, d, d};
    assign S = {b, c};
    mux4to1 m1(W,S,g);
    mux4to1 m2({g, 1'b0, 1'b0, 1'b0},{a, 1'b0},f);
endmodule

module mux4to1(W,S,f);
    input [0:3]W;
    input [1:0]S;
    output reg f;
    always@(W or S)
        f = S[1]?(S[0]?W[3]:W[2]):(S[0]?W[1]:W[0]);
endmodule

ques1b_tb.v
`timescale 1ns/1ns
`include "ques1b.v"

module ques1b_tb();
    reg a, b, c, d;
    wire f;
    ques1b test(a, b, c, d, f);
    initial begin
        $dumpfile("ques1b.vcd");
        $dumpvars(1,ques1b_tb);
        a=1'b0; b=1'b0; c=1'b0; d=1'b0; #10;
        a=1'b0; b=1'b0; c=1'b0; d=1'b1; #10;
        a=1'b0; b=1'b0; c=1'b1; d=1'b0; #10;
        a=1'b0; b=1'b0; c=1'b1; d=1'b1; #10;
        a=1'b0; b=1'b1; c=1'b0; d=1'b0; #10;
        a=1'b0; b=1'b1; c=1'b0; d=1'b1; #10;
        a=1'b0; b=1'b1; c=1'b1; d=1'b0; #10;
        a=1'b0; b=1'b1; c=1'b1; d=1'b1; #10;
        a=1'b1; b=1'b0; c=1'b0; d=1'b0; #10;
        a=1'b1; b=1'b0; c=1'b0; d=1'b1; #10;
        a=1'b1; b=1'b0; c=1'b1; d=1'b0; #10;
        a=1'b1; b=1'b0; c=1'b1; d=1'b1; #10;
        a=1'b1; b=1'b1; c=1'b0; d=1'b0; #10;
        a=1'b1; b=1'b1; c=1'b0; d=1'b1; #10;
        a=1'b1; b=1'b1; c=1'b1; d=1'b0; #10;
        a=1'b1; b=1'b1; c=1'b1; d=1'b1; #10;
        $display("Test completed");
    end
endmodule

ques1b.vcd
$date
	Tue Oct  4 09:53:23 2022
$end
$version
	Icarus Verilog
$end
$timescale
	1ns
$end
$scope module ques1b_tb $end
$var wire 1 ! f $end
$var reg 1 " a $end
$var reg 1 # b $end
$var reg 1 $ c $end
$var reg 1 % d $end
$upscope $end
$enddefinitions $end
#0
$dumpvars
0%
0$
0#
0"
0!
$end
#10
1!
1%
#20
0%
1$
#30
1%
#40
0!
0%
0$
1#
#50
1!
1%
#60
0!
0%
1$
#70
1!
1%
#80
0!
0%
0$
0#
1"
#90
1%
#100
0%
1$
#110
1%
#120
0%
0$
1#
#130
1%
#140
0%
1$
#150
1%
