ques1a.v
module ques1a(a, b, c, d, f);
    input a, b, c, d;
    output f;

    wire [0:7]W;
    wire [2:0]S;

    assign W = {1'b0, 1'b0, 1'b1, 1'b1, 1'b1, 1'b0, 1'b1, ~d};
    assign S = {a, b, c};
    mux8to1 m1(W,S,f);

endmodule

module mux8to1(W,S,f);
    input [0:7]W;
    input [2:0]S;
    output reg f;
    always@(W or S)
        case(S)
            0: f = W[0];
            1: f = W[1];
            2: f = W[2];
            3: f = W[3];
            4: f = W[4];
            5: f = W[5];
            6: f = W[6];
            7: f = W[7];
        endcase
endmodule

ques1a_tb.v
`timescale 1ns/1ns
`include "ques1a.v"

module ques1a_tb();
    reg a, b, c, d;
    wire f;
    ques1a test(a, b, c, d, f);
    initial begin
        $dumpfile("ques1a.vcd");
        $dumpvars(1,ques1a_tb);
        a=1'b0; b=1'b0; c=1'b0; d=1'b0; #10;
        a=1'b0; b=1'b0; c=1'b0; d=1'b1; #10;
        a=1'b0; b=1'b0; c=1'b1; d=1'b0; #10;
        a=1'b0; b=1'b0; c=1'b1; d=1'b1; #10;
        a=1'b0; b=1'b1; c=1'b0; d=1'b0; #10;
        a=1'b0; b=1'b1; c=1'b0; d=1'b1; #10;
        a=1'b0; b=1'b1; c=1'b1; d=1'b0; #10;
        a=1'b0; b=1'b1; c=1'b1; d=1'b1; #10;
        a=1'b1; b=1'b0; c=1'b0; d=1'b0; #10;
        a=1'b1; b=1'b0; c=1'b0; d=1'b1; #10;
        a=1'b1; b=1'b0; c=1'b1; d=1'b0; #10;
        a=1'b1; b=1'b0; c=1'b1; d=1'b1; #10;
        a=1'b1; b=1'b1; c=1'b0; d=1'b0; #10;
        a=1'b1; b=1'b1; c=1'b0; d=1'b1; #10;
        a=1'b1; b=1'b1; c=1'b1; d=1'b0; #10;
        a=1'b1; b=1'b1; c=1'b1; d=1'b1; #10;
        $display("Test completed");
    end
endmodule

ques1a.vcd
$date
	Tue Oct  4 09:30:03 2022
$end
$version
	Icarus Verilog
$end
$timescale
	1ns
$end
$scope module ques1a_tb $end
$var wire 1 ! f $end
$var reg 1 " a $end
$var reg 1 # b $end
$var reg 1 $ c $end
$var reg 1 % d $end
$upscope $end
$enddefinitions $end
#0
$dumpvars
0%
0$
0#
0"
0!
$end
#10
1%
#20
0%
1$
#30
1%
#40
1!
0%
0$
1#
#50
1%
#60
0%
1$
#70
1%
#80
0%
0$
0#
1"
#90
1%
#100
0!
0%
1$
#110
1%
#120
1!
0%
0$
1#
#130
1%
#140
1!
0%
1$
#150
0!
1%
